genexe/__init__.py
genexe/generate_exe.py
genexe/winicon.py
genexe/res/template
gen_exe-0.2.1.dist-info/LICENSE
gen_exe-0.2.1.dist-info/METADATA
gen_exe-0.2.1.dist-info/WHEEL
gen_exe-0.2.1.dist-info/entry_points.txt
gen_exe-0.2.1.dist-info/top_level.txt
gen_exe-0.2.1.dist-info/RECORD
