Metadata-Version: 2.1
Name: gen-exe
Version: 0.2.1
Summary: A small utility which allows you to generate Windows executables that can run custom commands on your Windows system.
Home-page: UNKNOWN
Author: S.C. van de Leemput
Author-email: silvandeleemput@gmail.com
License: LICENSE
Platform: UNKNOWN
Classifier: License :: OSI Approved :: MIT License
Classifier: Programming Language :: Python :: 3
Classifier: Programming Language :: C++
Classifier: Operating System :: Microsoft :: Windows
Classifier: Intended Audience :: Developers
Requires-Dist: click
Requires-Dist: pywin32
